ouverture_firefox/__init__.py
ouverture_firefox/ouverture_firefox.py
ouverture_firefox-1.0.0.dist-info/METADATA
ouverture_firefox-1.0.0.dist-info/WHEEL
ouverture_firefox-1.0.0.dist-info/top_level.txt
ouverture_firefox-1.0.0.dist-info/RECORD
